nonebot_plugin_styledstr/__init__.py
nonebot_plugin_styledstr/config.py
nonebot_plugin_styledstr/exception.py
nonebot_plugin_styledstr/styledstr.py
nonebot_plugin_styledstr-1.0.2.dist-info/LICENSE
nonebot_plugin_styledstr-1.0.2.dist-info/WHEEL
nonebot_plugin_styledstr-1.0.2.dist-info/METADATA
nonebot_plugin_styledstr-1.0.2.dist-info/RECORD
