Metadata-Version: 2.1
Name: nonebot-plugin-styledstr
Version: 1.0.2
Summary: A styled string management plugin for NoneBot 2
License: MIT
Author: Satoshi Jek
Author-email: jks15satoshi@gmail.com
Requires-Python: >=3.8,<4.0
Classifier: Development Status :: 5 - Production/Stable
Classifier: License :: OSI Approved :: MIT License
Classifier: Operating System :: OS Independent
Classifier: Programming Language :: Python :: 3
Classifier: Programming Language :: Python :: 3.8
Classifier: Programming Language :: Python :: 3.9
Classifier: Programming Language :: Python :: 3.10
Classifier: Programming Language :: Python :: 3
Classifier: Typing :: Typed
Requires-Dist: nonebot2 (>=2.0.0-alpha.11,<3.0.0)
Requires-Dist: pyyaml (>=5.4.1,<7.0.0)
